[
  {
    "_id": "676996271db096b3cc412d30",
    "index": 0,
    "guid": "5f41ba87-868f-4eaa-a5dc-08832d39abf3",
    "isActive": false,
    "balance": "$3,598.43",
    "picture": "http://placehold.it/32x32",
    "age": 36,
    "eyeColor": "brown",
    "name": "Austin Shannon",
    "gender": "male",
    "company": "QUILM",
    "email": "austinshannon@quilm.com",
    "phone": "+1 (949) 506-2109",
    "address": "724 Bayard Street, Biddle, Louisiana, 5764",
    "about": "Ipsum ipsum quis mollit officia ex Lorem consequat deserunt exercitation nisi labore adipisicing sint tempor. Ullamco eu ullamco dolore nostrud cupidatat dolor aliqua. Tempor nisi est eu sint minim labore nulla sunt laboris amet ullamco nisi. Dolor est irure ea eu adipisicing consectetur amet reprehenderit dolor excepteur velit et anim. Occaecat consequat irure officia velit ut ipsum ea excepteur in velit quis. Est occaecat veniam incididunt est ex eiusmod.\r\n",
    "registered": "2019-04-27T12:49:16 -01:00",
    "latitude": 33.335396,
    "longitude": -139.000864,
    "tags": [
      "eu",
      "eu",
      "qui",
      "mollit",
      "cupidatat",
      "pariatur",
      "magna"
    ],
    "friends": [
      {
        "id": 0,
        "name": "Jeri Goodman"
      },
      {
        "id": 1,
        "name": "Bradley Howard"
      },
      {
        "id": 2,
        "name": "Pollard Simpson"
      }
    ],
    "greeting": "Hello, Austin Shannon! You have 5 unread messages.",
    "favoriteFruit": "banana"
  },
  {
    "_id": "67699627156385be7656e583",
    "index": 1,
    "guid": "7efb7965-fd89-4573-a139-a559e5fc2ec2",
    "isActive": true,
    "balance": "$3,266.67",
    "picture": "http://placehold.it/32x32",
    "age": 32,
    "eyeColor": "brown",
    "name": "Annabelle Brennan",
    "gender": "female",
    "company": "POWERNET",
    "email": "annabellebrennan@powernet.com",
    "phone": "+1 (991) 549-2490",
    "address": "938 Duryea Court, Kieler, New Jersey, 4642",
    "about": "Aliqua ullamco Lorem cupidatat do minim elit et aliqua ut. Non ipsum aliquip id labore amet velit ad. Sint consectetur deserunt labore minim pariatur Lorem adipisicing ullamco commodo nulla minim. Pariatur duis aliquip tempor laborum ex magna elit veniam eu ullamco Lorem irure aute. Commodo consequat id magna nostrud aute sunt officia excepteur ea et pariatur in ad pariatur. Occaecat Lorem nostrud aute ex qui mollit aute fugiat fugiat enim in velit ullamco.\r\n",
    "registered": "2018-08-18T01:31:20 -01:00",
    "latitude": 9.293123,
    "longitude": 55.63776,
    "tags": [
      "amet",
      "magna",
      "nulla",
      "duis",
      "deserunt",
      "esse",
      "elit"
    ],
    "friends": [
      {
        "id": 0,
        "name": "Warren Barber"
      },
      {
        "id": 1,
        "name": "Cantu Bender"
      },
      {
        "id": 2,
        "name": "Jerri Yates"
      }
    ],
    "greeting": "Hello, Annabelle Brennan! You have 6 unread messages.",
    "favoriteFruit": "strawberry"
  },
  {
    "_id": "676996277f99c8c477630a1c",
    "index": 2,
    "guid": "555ae642-e00b-457c-8125-77d38f2e7472",
    "isActive": true,
    "balance": "$3,269.87",
    "picture": "http://placehold.it/32x32",
    "age": 21,
    "eyeColor": "brown",
    "name": "Summer Hahn",
    "gender": "female",
    "company": "CHILLIUM",
    "email": "summerhahn@chillium.com",
    "phone": "+1 (893) 405-2830",
    "address": "341 Colonial Road, Brownlee, Delaware, 6337",
    "about": "Amet adipisicing irure mollit elit eu. Velit nulla aliqua magna nostrud non proident. Nulla et Lorem eu est nulla sint eu ullamco excepteur labore. Ipsum adipisicing exercitation incididunt sint aute tempor duis aliquip ex labore deserunt. Tempor sit in ea sit labore qui incididunt duis.\r\n",
    "registered": "2023-11-05T05:49:33 -00:00",
    "latitude": -26.176782,
    "longitude": -97.019105,
    "tags": [
      "duis",
      "amet",
      "laboris",
      "culpa",
      "esse",
      "deserunt",
      "dolore"
    ],
    "friends": [
      {
        "id": 0,
        "name": "Jennings Craig"
      },
      {
        "id": 1,
        "name": "Morrison Sparks"
      },
      {
        "id": 2,
        "name": "Riggs Bartlett"
      }
    ],
    "greeting": "Hello, Summer Hahn! You have 3 unread messages.",
    "favoriteFruit": "banana"
  },
  {
    "_id": "676996273b43fa03781fda71",
    "index": 3,
    "guid": "63a023dc-3cd6-4eba-88fa-59ded01a421e",
    "isActive": false,
    "balance": "$1,526.84",
    "picture": "http://placehold.it/32x32",
    "age": 25,
    "eyeColor": "brown",
    "name": "Rutledge Shaw",
    "gender": "male",
    "company": "PORTICA",
    "email": "rutledgeshaw@portica.com",
    "phone": "+1 (842) 449-2615",
    "address": "893 Judge Street, Morgandale, Marshall Islands, 865",
    "about": "Amet velit eu elit sunt ea ex nostrud aute qui fugiat ut. Aliquip culpa ullamco aliquip nostrud enim in ipsum culpa laboris eu incididunt. Exercitation nulla amet duis ullamco consequat et sit et ullamco sint ex ea. Magna ad mollit reprehenderit velit aliquip dolor dolor reprehenderit cillum tempor do deserunt aliqua. Proident laborum consectetur Lorem aliquip Lorem eiusmod do voluptate pariatur laborum. Lorem laborum eiusmod consequat reprehenderit.\r\n",
    "registered": "2024-12-06T09:04:59 -00:00",
    "latitude": 16.993414,
    "longitude": -55.650552,
    "tags": [
      "consectetur",
      "dolor",
      "cillum",
      "sunt",
      "cillum",
      "deserunt",
      "magna"
    ],
    "friends": [
      {
        "id": 0,
        "name": "Miranda Whitley"
      },
      {
        "id": 1,
        "name": "Eva Ramirez"
      },
      {
        "id": 2,
        "name": "Barry Oneil"
      }
    ],
    "greeting": "Hello, Rutledge Shaw! You have 7 unread messages.",
    "favoriteFruit": "apple"
  },
  {
    "_id": "676996271dbb765badcadb78",
    "index": 4,
    "guid": "accb5655-e59e-402d-906c-0e6a92283226",
    "isActive": false,
    "balance": "$3,902.35",
    "picture": "http://placehold.it/32x32",
    "age": 24,
    "eyeColor": "brown",
    "name": "Blanche Morrow",
    "gender": "female",
    "company": "CINCYR",
    "email": "blanchemorrow@cincyr.com",
    "phone": "+1 (831) 547-2245",
    "address": "426 Hamilton Walk, Morningside, Wyoming, 4594",
    "about": "Velit sint proident anim officia elit aute labore anim. Tempor anim ea elit enim nulla duis ullamco laborum. Laboris adipisicing quis consequat incididunt veniam non magna pariatur ipsum excepteur fugiat duis. Officia reprehenderit velit qui aliquip laborum enim voluptate anim aliqua aliqua nisi ut. Elit quis velit ea pariatur deserunt ullamco consectetur pariatur ut laboris duis. Nisi adipisicing in laboris dolor in. Labore nostrud et deserunt aliqua minim duis pariatur veniam ipsum duis reprehenderit quis ipsum.\r\n",
    "registered": "2014-04-27T06:55:13 -01:00",
    "latitude": 48.893758,
    "longitude": 136.590274,
    "tags": [
      "elit",
      "incididunt",
      "ullamco",
      "laborum",
      "laboris",
      "dolor",
      "quis"
    ],
    "friends": [
      {
        "id": 0,
        "name": "Pope Levine"
      },
      {
        "id": 1,
        "name": "Cotton Sanford"
      },
      {
        "id": 2,
        "name": "Woodward Vargas"
      }
    ],
    "greeting": "Hello, Blanche Morrow! You have 4 unread messages.",
    "favoriteFruit": "apple"
  }
]
